CHANGELOG.md
prodmanager/__init__.py
prodmanager/base.py
prodmanager/client.py
prodmanager/log.py
prod_manager-0.2.0.dist-info/METADATA
prod_manager-0.2.0.dist-info/WHEEL
prod_manager-0.2.0.dist-info/RECORD
