Metadata-Version: 2.1
Name: prod-manager
Version: 0.2.0
Summary: Interact with a ProdManager instance
Home-page: https://gitlab.com/prod-manager/prod-manager-api
License: GPL-3.0
Keywords: prod-manager,manager,production,monitor,incident,maintenance
Author: Lunik
Author-email: lunik@tiwabbit.fr
Maintainer: Lunik
Maintainer-email: lunik@tiwabbit.fr
Requires-Python: >=3.7,<4.0
Classifier: Development Status :: 4 - Beta
Classifier: Environment :: Console
Classifier: Intended Audience :: Developers
Classifier: Intended Audience :: Information Technology
Classifier: Intended Audience :: System Administrators
Classifier: License :: OSI Approved :: GNU General Public License v3 (GPLv3)
Classifier: Natural Language :: English
Classifier: Operating System :: POSIX
Classifier: Programming Language :: Python :: 3
Classifier: Programming Language :: Python :: 3.7
Classifier: Programming Language :: Python :: 3.8
Classifier: Programming Language :: Python :: 3.9
Classifier: Programming Language :: Python :: 3.10
Classifier: Programming Language :: Python :: 3.11
Classifier: Topic :: System :: Monitoring
Classifier: Topic :: System :: Systems Administration
Classifier: Topic :: Utilities
Requires-Dist: requests (>=2.13.0,<3.0.0)
Project-URL: Bug Tracker, https://gitlab.com/prod-manager/prod-manager-api/-/issues
Project-URL: Documentation, https://prod-manager-api.tiwabbit.fr
Project-URL: Repository, https://gitlab.com/prod-manager/prod-manager-api
